[{"courseID":"287224","subNum":"TEE 4930","desc":"Independent Study"},{"courseID":"287225","subNum":"TEE 4940","desc":"Related Industrial Experience"},{"courseID":"287226","subNum":"TEE 5040","desc":"Manufacturing Enterprise"},{"courseID":"291844","subNum":"TEE 5200","desc":"Advanced Aquaponic Systems"},{"courseID":"287227","subNum":"TEE 5220","desc":"Program and Course Development (CI)"},{"courseID":"287228","subNum":"TEE 5230","desc":"Technical Training Innovative Program"},{"courseID":"287229","subNum":"TEE 5240","desc":"Principles of Technology"},{"courseID":"287230","subNum":"TEE 5500","desc":"Student Teaching Seminar"},{"courseID":"287231","subNum":"TEE 5630","desc":"Student Teaching in Secondary Schools"},{"courseID":"287232","subNum":"TEE 5800","desc":"Seminar - Technology Education"},{"courseID":"287233","subNum":"TEE 5900","desc":"Workshop in Technology and Engineering Education"},{"courseID":"287234","subNum":"TEE 5910","desc":"Special Problems in Engineering and Technology Education"},{"courseID":"287235","subNum":"TEE 5920","desc":"Related Technical Training"},{"courseID":"287239","subNum":"TEE 6200","desc":"Composite Manufacturing Processes and Repair"},{"courseID":"287240","subNum":"TEE 6250","desc":"Internship"},{"courseID":"287241","subNum":"TEE 6310","desc":"Corrosion and Corrosion Control"},{"courseID":"287242","subNum":"TEE 6440","desc":"Technology and Society: Linking CTE with STEM"},{"courseID":"287244","subNum":"TEE 6520","desc":"Explorations of Industry"},{"courseID":"287250","subNum":"TEE 6960","desc":"Master's Project"},{"courseID":"287255","subNum":"TEE 7040","desc":"Dynamic and Network Engineering Processes for Technology Education"},{"courseID":"287257","subNum":"TEE 7400","desc":"Occupational Analysis and Curriculum Development"},{"courseID":"287260","subNum":"TEE 7600","desc":"Academic Issues and Politics in Higher Education"},{"courseID":"293643","subNum":"TESY 1200","desc":"Computer-Aided Drafting and Design"},{"courseID":"292626","subNum":"TESY 1020","desc":"Energy, Power, Transportation Systems Control Technology"},{"courseID":"292625","subNum":"TESY 1030","desc":"Material Processing Systems"},{"courseID":"292493","subNum":"TESY 2250","desc":"Occupational Experience in General Technology"},{"courseID":"292111","subNum":"TESY 2940","desc":"Related Industry Experience and Credential"},{"courseID":"291957","subNum":"TESY 3000","desc":"Hazard Recognition & Control"},{"courseID":"291784","subNum":"TESY 3020","desc":"Technology Enterprises"},{"courseID":"292628","subNum":"TESY 3030","desc":"Computer-Integrated Manufacturing Systems"},{"courseID":"293704","subNum":"TESY 3040","desc":"Design for Additive Manufacturing"},{"courseID":"302035","subNum":"TESY 3100","desc":"Digital Tools for Learning"},{"courseID":"293705","subNum":"TESY 3120","desc":"Classroom and Laboratory Management"},{"courseID":"293645","subNum":"TESY 3270","desc":"Advanced Computer-Aided Drafting"},{"courseID":"292440","subNum":"TESY 3300","desc":"Electronic Systems and Programming"},{"courseID":"292495","subNum":"TESY 3900","desc":"Independent Study in Technology Systems"},{"courseID":"292627","subNum":"TESY 4230","desc":"Advanced Materials and Processing Systems"},{"courseID":"292121","subNum":"TESY 4250","desc":"Internship in Technology Systems"},{"courseID":"293706","subNum":"TESY 4300","desc":"Intellectual Property for Product Developers"},{"courseID":"293707","subNum":"TESY 4330","desc":"Product Innovation Processes, Tools, and Strategies"},{"courseID":"293708","subNum":"TESY 4410","desc":"Industrial Automation and Networking"},{"courseID":"293709","subNum":"TESY 4420","desc":"Industrial Robotics"},{"courseID":"293710","subNum":"TESY 4430","desc":"Advanced Programmable Logic Controllers"},{"courseID":"293711","subNum":"TESY 4440","desc":"Machine Vision and Inspection"},{"courseID":"293712","subNum":"TESY 4450","desc":"Human Machine Interface"},{"courseID":"292106","subNum":"TESY 4500","desc":"Quality Management Systems"},{"courseID":"292108","subNum":"TESY 4510","desc":"Quality Root Cause Analysis Methods and Applications"},{"courseID":"292104","subNum":"TESY 4520","desc":"Statistical Quality Control w/SPC"},{"courseID":"292107","subNum":"TESY 4530","desc":"Principles of Lean Manufacturing"},{"courseID":"292105","subNum":"TESY 4540","desc":"Quality Management Systems II"},{"courseID":"292124","subNum":"TESY 4720","desc":"IT Management"},{"courseID":"292122","subNum":"TESY 4730","desc":"Cloud Computing"},{"courseID":"292123","subNum":"TESY 4740","desc":"Disaster Recovery and Business Resumption"},{"courseID":"292148","subNum":"TESY 4750","desc":"Network Administration"},{"courseID":"292290","subNum":"TESY 4810","desc":"Linux Essentials with Kali"},{"courseID":"292291","subNum":"TESY 4820","desc":"Penetration Testing"},{"courseID":"292292","subNum":"TESY 4830","desc":"Network Defense and Traffic Analysis"},{"courseID":"291956","subNum":"TESY 4840","desc":"Security and Digital Forensics"},{"courseID":"292293","subNum":"TESY 4850","desc":"Advanced Python"},{"courseID":"292494","subNum":"TESY 4900","desc":"Senior Project in Technology Systems"},{"courseID":"292120","subNum":"TESY 4940","desc":"Related Occupational/Industrial Experience"},{"courseID":"292492","subNum":"TESY 5910","desc":"Special Problems in Technology Systems"},{"courseID":"290189","subNum":"THEA 1000","desc":"Acting I: Introduction to Acting (BCA)"},{"courseID":"290200","subNum":"THEA 1010","desc":"Acting II: Audition Preparation"},{"courseID":"290190","subNum":"THEA 1013","desc":"Understanding Theatre (BCA)"},{"courseID":"290191","subNum":"THEA 1023","desc":"Introduction to Film (BCA)"},{"courseID":"290193","subNum":"THEA 1033","desc":"Beginning Acting (BCA)"},{"courseID":"290632","subNum":"THEA 1050","desc":"Orientation for Actors"},{"courseID":"290194","subNum":"THEA 1113","desc":"Voice for Actors I"},{"courseID":"290196","subNum":"THEA 1210","desc":"Movement for Actors"},{"courseID":"290195","subNum":"THEA 1223","desc":"Stage Makeup"},{"courseID":"290881","subNum":"THEA 1310","desc":"Theatre Education Seminar"},{"courseID":"290197","subNum":"THEA 1513","desc":"Stagecraft (BCA)"},{"courseID":"290198","subNum":"THEA 1713","desc":"Playscript Analysis (BHU)"},{"courseID":"290199","subNum":"THEA 2000","desc":"Acting III: Scene Study-Text as Action"},{"courseID":"290206","subNum":"THEA 2010","desc":"Acting IV: Shakespeare"},{"courseID":"292441","subNum":"THEA 2033","desc":"Scene Study"},{"courseID":"290205","subNum":"THEA 2100","desc":"Voice for Actors II: Speech and IPA"},{"courseID":"290226","subNum":"THEA 2110","desc":"Voice for Actors III: Dialects"},{"courseID":"290225","subNum":"THEA 2200","desc":"Ballet"},{"courseID":"290201","subNum":"THEA 2203","desc":"Costume Construction and Technology"},{"courseID":"290223","subNum":"THEA 2210","desc":"Jazz"},{"courseID":"290203","subNum":"THEA 2220","desc":"Advanced Movement for Actors"},{"courseID":"290249","subNum":"THEA 2370","desc":"Applied Theatre"},{"courseID":"290633","subNum":"THEA 2500","desc":"Drafting for Theatre I"},{"courseID":"290207","subNum":"THEA 2510","desc":"Scene Painting"},{"courseID":"290228","subNum":"THEA 2520","desc":"Costume Design I"},{"courseID":"290211","subNum":"THEA 2530","desc":"Theatre and Studio Sound"},{"courseID":"290208","subNum":"THEA 2540","desc":"Lighting Design I"},{"courseID":"292209","subNum":"THEA 2550","desc":"Stage Management"},{"courseID":"290210","subNum":"THEA 2555","desc":"Production Practicum"},{"courseID":"290227","subNum":"THEA 2560","desc":"Scene Design I"},{"courseID":"290794","subNum":"THEA 2570","desc":"Theatre Props and Crafts"},{"courseID":"290240","subNum":"THEA 2575","desc":"Production Projects"},{"courseID":"292658","subNum":"THEA 2580","desc":"Costume Construction II"},{"courseID":"291255","subNum":"THEA 2610","desc":"Directing I"},{"courseID":"290212","subNum":"THEA 2666","desc":"Theatre Apprenticeship for High School Students"},{"courseID":"290213","subNum":"THEA 2670","desc":"Costume History"},{"courseID":"290692","subNum":"THEA 2710","desc":"The Art of Storytelling"},{"courseID":"290214","subNum":"THEA 2910","desc":"Private Instruction in Theatre Arts"}]